{
    "Num species": 12,
    "Species 7 num animals": 5,
    "Species 7 top fitness": -1113.564725917709,
    "Species 7 mean fitness": -1271.6126544304734,
    "Species 7 std fitness": 139.26125368335568,
    "Species 7 top animal N hidden neurons": 1,
    "Species 7 top animal N synapses": 7,
    "Species 7 top animal": {
        "neurons": {
            "0": {
                "type": "i",
                "bias": null
            },
            "1": {
                "type": "i",
                "bias": null
            },
            "2": {
                "type": "i",
                "bias": null
            },
            "3": {
                "type": "o",
                "bias": null
            },
            "23": {
                "type": "h",
                "bias": 0.623839109924066
            }
        },
        "synapses": {
            "35": {
                "active": true,
                "nrn_to": 23,
                "nrn_from": 1,
                "weight": 2.81339266596519
            },
            "4": {
                "active": true,
                "nrn_to": 3,
                "nrn_from": 0,
                "weight": -0.6860428667596162
            },
            "5": {
                "active": true,
                "nrn_to": 3,
                "nrn_from": 2,
                "weight": 0.1662919668137717
            },
            "69": {
                "active": true,
                "nrn_to": 23,
                "nrn_from": 2,
                "weight": 0.6483887352844673
            },
            "6": {
                "active": true,
                "nrn_to": 3,
                "nrn_from": 1,
                "weight": 0.23921295850476687
            },
            "24": {
                "active": true,
                "nrn_to": 23,
                "nrn_from": 0,
                "weight": 2.7847366977488037
            },
            "25": {
                "active": true,
                "nrn_to": 3,
                "nrn_from": 23,
                "weight": -0.6465812107700993
            }
        }
    },
    "Species 3 num animals": 9,
    "Species 3 top fitness": -1227.7827661751712,
    "Species 3 mean fitness": -1284.8265125788214,
    "Species 3 std fitness": 90.91724113434721,
    "Species 3 top animal N hidden neurons": 1,
    "Species 3 top animal N synapses": 7,
    "Species 3 top animal": {
        "neurons": {
            "0": {
                "type": "i",
                "bias": null
            },
            "1": {
                "type": "i",
                "bias": null
            },
            "2": {
                "type": "i",
                "bias": null
            },
            "3": {
                "type": "o",
                "bias": null
            },
            "32": {
                "type": "h",
                "bias": -0.38577747837747944
            }
        },
        "synapses": {
            "33": {
                "active": true,
                "nrn_to": 32,
                "nrn_from": 0,
                "weight": 0.5716203514332011
            },
            "34": {
                "active": false,
                "nrn_to": 3,
                "nrn_from": 32,
                "weight": 0.026961566342030036
            },
            "4": {
                "active": true,
                "nrn_to": 3,
                "nrn_from": 0,
                "weight": -0.2929810139226574
            },
            "5": {
                "active": true,
                "nrn_to": 3,
                "nrn_from": 2,
                "weight": 0.10065709652633656
            },
            "6": {
                "active": true,
                "nrn_to": 3,
                "nrn_from": 1,
                "weight": 0.4679848913629937
            },
            "56": {
                "active": false,
                "nrn_to": 32,
                "nrn_from": 1,
                "weight": -0.0011301031038060735
            },
            "76": {
                "active": true,
                "nrn_to": 32,
                "nrn_from": 2,
                "weight": -0.286779342894018
            }
        }
    },
    "Species 12 num animals": 4,
    "Species 12 top fitness": -1001.6815780954239,
    "Species 12 mean fitness": -1035.125976921221,
    "Species 12 std fitness": 33.48851003351296,
    "Species 12 top animal N hidden neurons": 3,
    "Species 12 top animal N synapses": 14,
    "Species 12 top animal": {
        "neurons": {
            "0": {
                "type": "i",
                "bias": null
            },
            "1": {
                "type": "i",
                "bias": null
            },
            "2": {
                "type": "i",
                "bias": null
            },
            "3": {
                "type": "o",
                "bias": null
            },
            "202": {
                "type": "h",
                "bias": -0.23687901470249584
            },
            "23": {
                "type": "h",
                "bias": -0.08311558566522709
            },
            "347": {
                "type": "h",
                "bias": null
            }
        },
        "synapses": {
            "225": {
                "active": true,
                "nrn_to": 202,
                "nrn_from": 2,
                "weight": -0.6669238112564473
            },
            "35": {
                "active": false,
                "nrn_to": 23,
                "nrn_from": 1,
                "weight": -0.002878355185397752
            },
            "4": {
                "active": true,
                "nrn_to": 3,
                "nrn_from": 0,
                "weight": -1.5563503615057024
            },
            "5": {
                "active": true,
                "nrn_to": 3,
                "nrn_from": 2,
                "weight": 0.23384727280317238
            },
            "69": {
                "active": true,
                "nrn_to": 23,
                "nrn_from": 2,
                "weight": 0.32430622681887555
            },
            "6": {
                "active": true,
                "nrn_to": 3,
                "nrn_from": 1,
                "weight": -0.3832136873504915
            },
            "203": {
                "active": true,
                "nrn_to": 202,
                "nrn_from": 1,
                "weight": 2.4798916706653182
            },
            "204": {
                "active": false,
                "nrn_to": 23,
                "nrn_from": 202,
                "weight": 1.066081428445897
            },
            "214": {
                "active": true,
                "nrn_to": 202,
                "nrn_from": 0,
                "weight": 0.11726193770527543
            },
            "24": {
                "active": true,
                "nrn_to": 23,
                "nrn_from": 0,
                "weight": 1.5951012482728417
            },
            "25": {
                "active": true,
                "nrn_to": 3,
                "nrn_from": 23,
                "weight": -3.0
            },
            "348": {
                "active": true,
                "nrn_to": 347,
                "nrn_from": 202,
                "weight": 1.0
            },
            "349": {
                "active": true,
                "nrn_to": 23,
                "nrn_from": 347,
                "weight": 1.066081428445897
            },
            "356": {
                "active": true,
                "nrn_to": 3,
                "nrn_from": 347,
                "weight": -0.32938525757972004
            }
        }
    },
    "Species 0 num animals": 7,
    "Species 0 top fitness": -1107.3728885660357,
    "Species 0 mean fitness": -1265.7316513279002,
    "Species 0 std fitness": 107.93590576907947,
    "Species 0 top animal N hidden neurons": 1,
    "Species 0 top animal N synapses": 7,
    "Species 0 top animal": {
        "neurons": {
            "0": {
                "type": "i",
                "bias": null
            },
            "1": {
                "type": "i",
                "bias": null
            },
            "2": {
                "type": "i",
                "bias": null
            },
            "3": {
                "type": "o",
                "bias": null
            },
            "39": {
                "type": "h",
                "bias": 0.3611574245258882
            }
        },
        "synapses": {
            "4": {
                "active": true,
                "nrn_to": 3,
                "nrn_from": 0,
                "weight": -0.5898023334173477
            },
            "100": {
                "active": true,
                "nrn_to": 39,
                "nrn_from": 2,
                "weight": 0.8041981900699936
            },
            "5": {
                "active": true,
                "nrn_to": 3,
                "nrn_from": 2,
                "weight": 0.262953766000359
            },
            "6": {
                "active": false,
                "nrn_to": 3,
                "nrn_from": 1,
                "weight": -0.010350541350542669
            },
            "40": {
                "active": true,
                "nrn_to": 39,
                "nrn_from": 0,
                "weight": 2.140215374366624
            },
            "41": {
                "active": true,
                "nrn_to": 3,
                "nrn_from": 39,
                "weight": -0.41213983916938585
            },
            "122": {
                "active": false,
                "nrn_to": 39,
                "nrn_from": 1,
                "weight": -0.4840264089051036
            }
        }
    },
    "Species 2 num animals": 10,
    "Species 2 top fitness": -1054.7807557318063,
    "Species 2 mean fitness": -1184.9273068741447,
    "Species 2 std fitness": 134.40594838450883,
    "Species 2 top animal N hidden neurons": 2,
    "Species 2 top animal N synapses": 10,
    "Species 2 top animal": {
        "neurons": {
            "0": {
                "type": "i",
                "bias": null
            },
            "1": {
                "type": "i",
                "bias": null
            },
            "2": {
                "type": "i",
                "bias": null
            },
            "3": {
                "type": "o",
                "bias": null
            },
            "336": {
                "type": "h",
                "bias": null
            },
            "23": {
                "type": "h",
                "bias": -0.5219821956453583
            }
        },
        "synapses": {
            "35": {
                "active": false,
                "nrn_to": 23,
                "nrn_from": 1,
                "weight": 1.5284639457962785
            },
            "4": {
                "active": true,
                "nrn_to": 3,
                "nrn_from": 0,
                "weight": -0.8242810665550033
            },
            "5": {
                "active": true,
                "nrn_to": 3,
                "nrn_from": 2,
                "weight": 0.316388127200835
            },
            "69": {
                "active": true,
                "nrn_to": 23,
                "nrn_from": 2,
                "weight": 0.7774035050123534
            },
            "6": {
                "active": false,
                "nrn_to": 3,
                "nrn_from": 1,
                "weight": 0.3982466126740597
            },
            "337": {
                "active": true,
                "nrn_to": 336,
                "nrn_from": 1,
                "weight": 1.0983718239898568
            },
            "338": {
                "active": true,
                "nrn_to": 23,
                "nrn_from": 336,
                "weight": 1.848043281201467
            },
            "24": {
                "active": true,
                "nrn_to": 23,
                "nrn_from": 0,
                "weight": 2.129144644603816
            },
            "25": {
                "active": true,
                "nrn_to": 3,
                "nrn_from": 23,
                "weight": -0.4984616669906111
            },
            "365": {
                "active": true,
                "nrn_to": 336,
                "nrn_from": 2,
                "weight": 0.17208832759578524
            }
        }
    },
    "Species 4 num animals": 10,
    "Species 4 top fitness": -1048.7093501037825,
    "Species 4 mean fitness": -1105.1274142686782,
    "Species 4 std fitness": 59.96615381550895,
    "Species 4 top animal N hidden neurons": 2,
    "Species 4 top animal N synapses": 12,
    "Species 4 top animal": {
        "neurons": {
            "0": {
                "type": "i",
                "bias": null
            },
            "1": {
                "type": "i",
                "bias": null
            },
            "2": {
                "type": "i",
                "bias": null
            },
            "3": {
                "type": "o",
                "bias": null
            },
            "202": {
                "type": "h",
                "bias": null
            },
            "23": {
                "type": "h",
                "bias": null
            }
        },
        "synapses": {
            "224": {
                "active": true,
                "nrn_to": 3,
                "nrn_from": 202,
                "weight": -0.23674999966204652
            },
            "225": {
                "active": true,
                "nrn_to": 202,
                "nrn_from": 2,
                "weight": -1.2662450660794364
            },
            "35": {
                "active": true,
                "nrn_to": 23,
                "nrn_from": 1,
                "weight": -0.33869627626845056
            },
            "4": {
                "active": true,
                "nrn_to": 3,
                "nrn_from": 0,
                "weight": -0.39240997086013346
            },
            "69": {
                "active": true,
                "nrn_to": 23,
                "nrn_from": 2,
                "weight": 0.5792178359998824
            },
            "5": {
                "active": true,
                "nrn_to": 3,
                "nrn_from": 2,
                "weight": 0.18563696401079738
            },
            "6": {
                "active": true,
                "nrn_to": 3,
                "nrn_from": 1,
                "weight": 0.6794902074327624
            },
            "203": {
                "active": true,
                "nrn_to": 202,
                "nrn_from": 1,
                "weight": 0.9408484860028085
            },
            "204": {
                "active": true,
                "nrn_to": 23,
                "nrn_from": 202,
                "weight": 0.8388333952942736
            },
            "214": {
                "active": true,
                "nrn_to": 202,
                "nrn_from": 0,
                "weight": 0.20333819744084328
            },
            "24": {
                "active": true,
                "nrn_to": 23,
                "nrn_from": 0,
                "weight": 2.623705405524605
            },
            "25": {
                "active": true,
                "nrn_to": 3,
                "nrn_from": 23,
                "weight": -0.5953852231030616
            }
        }
    },
    "Species 11 num animals": 12,
    "Species 11 top fitness": -1051.410213072765,
    "Species 11 mean fitness": -1154.5879597737905,
    "Species 11 std fitness": 90.69490758512687,
    "Species 11 top animal N hidden neurons": 3,
    "Species 11 top animal N synapses": 15,
    "Species 11 top animal": {
        "neurons": {
            "0": {
                "type": "i",
                "bias": null
            },
            "1": {
                "type": "i",
                "bias": null
            },
            "2": {
                "type": "i",
                "bias": null
            },
            "3": {
                "type": "o",
                "bias": null
            },
            "324": {
                "type": "h",
                "bias": null
            },
            "202": {
                "type": "h",
                "bias": 0.1364179539802403
            },
            "23": {
                "type": "h",
                "bias": null
            }
        },
        "synapses": {
            "224": {
                "active": true,
                "nrn_to": 3,
                "nrn_from": 202,
                "weight": 0.19943157348161478
            },
            "225": {
                "active": true,
                "nrn_to": 202,
                "nrn_from": 2,
                "weight": -1.4966783637618397
            },
            "35": {
                "active": true,
                "nrn_to": 23,
                "nrn_from": 1,
                "weight": -0.07713690354366856
            },
            "4": {
                "active": true,
                "nrn_to": 3,
                "nrn_from": 0,
                "weight": -0.47708619863068163
            },
            "5": {
                "active": true,
                "nrn_to": 3,
                "nrn_from": 2,
                "weight": 0.3214992653889827
            },
            "325": {
                "active": true,
                "nrn_to": 324,
                "nrn_from": 202,
                "weight": 1.0385280967416344
            },
            "69": {
                "active": true,
                "nrn_to": 23,
                "nrn_from": 2,
                "weight": 0.5443083337219617
            },
            "6": {
                "active": true,
                "nrn_to": 3,
                "nrn_from": 1,
                "weight": 0.13723941746028406
            },
            "326": {
                "active": true,
                "nrn_to": 23,
                "nrn_from": 324,
                "weight": 0.9559927586409638
            },
            "203": {
                "active": true,
                "nrn_to": 202,
                "nrn_from": 1,
                "weight": 1.282886331211046
            },
            "204": {
                "active": false,
                "nrn_to": 23,
                "nrn_from": 202,
                "weight": 0.8328760464742777
            },
            "339": {
                "active": false,
                "nrn_to": 324,
                "nrn_from": 0,
                "weight": 0.19952587132665028
            },
            "214": {
                "active": true,
                "nrn_to": 202,
                "nrn_from": 0,
                "weight": 0.249441760570326
            },
            "24": {
                "active": true,
                "nrn_to": 23,
                "nrn_from": 0,
                "weight": 2.937304203262151
            },
            "25": {
                "active": true,
                "nrn_to": 3,
                "nrn_from": 23,
                "weight": -2.051109921249682
            }
        }
    },
    "Species 9 num animals": 10,
    "Species 9 top fitness": -1146.1326770796368,
    "Species 9 mean fitness": -1273.84566240341,
    "Species 9 std fitness": 112.77037133384648,
    "Species 9 top animal N hidden neurons": 2,
    "Species 9 top animal N synapses": 12,
    "Species 9 top animal": {
        "neurons": {
            "0": {
                "type": "i",
                "bias": null
            },
            "1": {
                "type": "i",
                "bias": null
            },
            "2": {
                "type": "i",
                "bias": null
            },
            "3": {
                "type": "o",
                "bias": null
            },
            "202": {
                "type": "h",
                "bias": null
            },
            "23": {
                "type": "h",
                "bias": null
            }
        },
        "synapses": {
            "224": {
                "active": true,
                "nrn_to": 3,
                "nrn_from": 202,
                "weight": -0.4387467382412935
            },
            "225": {
                "active": true,
                "nrn_to": 202,
                "nrn_from": 2,
                "weight": -1.4259154692649982
            },
            "35": {
                "active": true,
                "nrn_to": 23,
                "nrn_from": 1,
                "weight": -0.5559181188076057
            },
            "4": {
                "active": true,
                "nrn_to": 3,
                "nrn_from": 0,
                "weight": -2.831498694158974
            },
            "69": {
                "active": true,
                "nrn_to": 23,
                "nrn_from": 2,
                "weight": 0.9381771083166892
            },
            "5": {
                "active": true,
                "nrn_to": 3,
                "nrn_from": 2,
                "weight": 0.35213326307425974
            },
            "6": {
                "active": true,
                "nrn_to": 3,
                "nrn_from": 1,
                "weight": -0.3256166442854536
            },
            "203": {
                "active": true,
                "nrn_to": 202,
                "nrn_from": 1,
                "weight": 0.6559777505508215
            },
            "204": {
                "active": true,
                "nrn_to": 23,
                "nrn_from": 202,
                "weight": 0.9825591035342998
            },
            "214": {
                "active": true,
                "nrn_to": 202,
                "nrn_from": 0,
                "weight": 0.641610972479216
            },
            "24": {
                "active": true,
                "nrn_to": 23,
                "nrn_from": 0,
                "weight": 0.760839483561865
            },
            "25": {
                "active": true,
                "nrn_to": 3,
                "nrn_from": 23,
                "weight": -0.5440306253424315
            }
        }
    },
    "Species 10 num animals": 10,
    "Species 10 top fitness": -1025.9773112841576,
    "Species 10 mean fitness": -1155.0238404436175,
    "Species 10 std fitness": 140.80293829187886,
    "Species 10 top animal N hidden neurons": 3,
    "Species 10 top animal N synapses": 14,
    "Species 10 top animal": {
        "neurons": {
            "0": {
                "type": "i",
                "bias": null
            },
            "1": {
                "type": "i",
                "bias": null
            },
            "2": {
                "type": "i",
                "bias": null
            },
            "3": {
                "type": "o",
                "bias": null
            },
            "202": {
                "type": "h",
                "bias": null
            },
            "23": {
                "type": "h",
                "bias": null
            },
            "362": {
                "type": "h",
                "bias": null
            }
        },
        "synapses": {
            "224": {
                "active": false,
                "nrn_to": 3,
                "nrn_from": 202,
                "weight": -0.10861262430738254
            },
            "225": {
                "active": true,
                "nrn_to": 202,
                "nrn_from": 2,
                "weight": -1.4630120567074008
            },
            "35": {
                "active": true,
                "nrn_to": 23,
                "nrn_from": 1,
                "weight": -1.0423100744332816
            },
            "4": {
                "active": true,
                "nrn_to": 3,
                "nrn_from": 0,
                "weight": -0.42377095697886996
            },
            "69": {
                "active": true,
                "nrn_to": 23,
                "nrn_from": 2,
                "weight": 0.7480223560778465
            },
            "5": {
                "active": true,
                "nrn_to": 3,
                "nrn_from": 2,
                "weight": 0.4124899208574727
            },
            "6": {
                "active": true,
                "nrn_to": 3,
                "nrn_from": 1,
                "weight": 0.629787915132111
            },
            "203": {
                "active": false,
                "nrn_to": 202,
                "nrn_from": 1,
                "weight": 1.1854931146855965
            },
            "204": {
                "active": true,
                "nrn_to": 23,
                "nrn_from": 202,
                "weight": 1.39186347610552
            },
            "214": {
                "active": true,
                "nrn_to": 202,
                "nrn_from": 0,
                "weight": 0.008160787131647043
            },
            "24": {
                "active": true,
                "nrn_to": 23,
                "nrn_from": 0,
                "weight": 2.4464811791045795
            },
            "25": {
                "active": true,
                "nrn_to": 3,
                "nrn_from": 23,
                "weight": -0.8132526949765486
            },
            "363": {
                "active": true,
                "nrn_to": 362,
                "nrn_from": 1,
                "weight": 1.0
            },
            "364": {
                "active": true,
                "nrn_to": 202,
                "nrn_from": 362,
                "weight": 1.1854931146855965
            }
        }
    },
    "Species 5 num animals": 8,
    "Species 5 top fitness": -1112.4623938784248,
    "Species 5 mean fitness": -1124.3467753479067,
    "Species 5 std fitness": 15.878837568817875,
    "Species 5 top animal N hidden neurons": 1,
    "Species 5 top animal N synapses": 7,
    "Species 5 top animal": {
        "neurons": {
            "0": {
                "type": "i",
                "bias": null
            },
            "1": {
                "type": "i",
                "bias": null
            },
            "2": {
                "type": "i",
                "bias": null
            },
            "3": {
                "type": "o",
                "bias": null
            },
            "123": {
                "type": "h",
                "bias": null
            }
        },
        "synapses": {
            "194": {
                "active": true,
                "nrn_to": 123,
                "nrn_from": 2,
                "weight": -0.8857169991117366
            },
            "4": {
                "active": true,
                "nrn_to": 3,
                "nrn_from": 0,
                "weight": -0.7954345770013594
            },
            "5": {
                "active": false,
                "nrn_to": 3,
                "nrn_from": 2,
                "weight": -0.2610398456107039
            },
            "6": {
                "active": true,
                "nrn_to": 3,
                "nrn_from": 1,
                "weight": 0.3004060550794418
            },
            "181": {
                "active": false,
                "nrn_to": 123,
                "nrn_from": 0,
                "weight": 0.265615374552144
            },
            "124": {
                "active": true,
                "nrn_to": 123,
                "nrn_from": 1,
                "weight": 1.0790684887276611
            },
            "125": {
                "active": true,
                "nrn_to": 3,
                "nrn_from": 123,
                "weight": -0.584099166107965
            }
        }
    },
    "Species 8 num animals": 9,
    "Species 8 top fitness": -1001.0627903268775,
    "Species 8 mean fitness": -1098.9068654072078,
    "Species 8 std fitness": 118.44559705050204,
    "Species 8 top animal N hidden neurons": 2,
    "Species 8 top animal N synapses": 11,
    "Species 8 top animal": {
        "neurons": {
            "0": {
                "type": "i",
                "bias": null
            },
            "1": {
                "type": "i",
                "bias": null
            },
            "2": {
                "type": "i",
                "bias": null
            },
            "3": {
                "type": "o",
                "bias": null
            },
            "202": {
                "type": "h",
                "bias": -0.23687901470249584
            },
            "23": {
                "type": "h",
                "bias": -0.08311558566522709
            }
        },
        "synapses": {
            "225": {
                "active": true,
                "nrn_to": 202,
                "nrn_from": 2,
                "weight": -1.467773269642272
            },
            "35": {
                "active": false,
                "nrn_to": 23,
                "nrn_from": 1,
                "weight": -0.005756710370795504
            },
            "4": {
                "active": true,
                "nrn_to": 3,
                "nrn_from": 0,
                "weight": -0.882065197847516
            },
            "5": {
                "active": true,
                "nrn_to": 3,
                "nrn_from": 2,
                "weight": 0.45326471054970907
            },
            "69": {
                "active": true,
                "nrn_to": 23,
                "nrn_from": 2,
                "weight": 0.4396254181202191
            },
            "6": {
                "active": true,
                "nrn_to": 3,
                "nrn_from": 1,
                "weight": 0.07004331946125039
            },
            "203": {
                "active": true,
                "nrn_to": 202,
                "nrn_from": 1,
                "weight": 2.1955342014565415
            },
            "204": {
                "active": true,
                "nrn_to": 23,
                "nrn_from": 202,
                "weight": 1.023493442109251
            },
            "214": {
                "active": false,
                "nrn_to": 202,
                "nrn_from": 0,
                "weight": 0.3113083416612178
            },
            "24": {
                "active": true,
                "nrn_to": 23,
                "nrn_from": 0,
                "weight": 1.4197308269575792
            },
            "25": {
                "active": true,
                "nrn_to": 3,
                "nrn_from": 23,
                "weight": -1.8668260831851318
            }
        }
    },
    "Species 6 num animals": 6,
    "Species 6 top fitness": -1044.0740266982534,
    "Species 6 mean fitness": -1084.8371048462157,
    "Species 6 std fitness": 61.31370128978661,
    "Species 6 top animal N hidden neurons": 2,
    "Species 6 top animal N synapses": 12,
    "Species 6 top animal": {
        "neurons": {
            "0": {
                "type": "i",
                "bias": null
            },
            "1": {
                "type": "i",
                "bias": null
            },
            "2": {
                "type": "i",
                "bias": null
            },
            "3": {
                "type": "o",
                "bias": null
            },
            "202": {
                "type": "h",
                "bias": null
            },
            "23": {
                "type": "h",
                "bias": -0.08311558566522709
            }
        },
        "synapses": {
            "225": {
                "active": true,
                "nrn_to": 202,
                "nrn_from": 2,
                "weight": -1.337238834981919
            },
            "35": {
                "active": true,
                "nrn_to": 23,
                "nrn_from": 1,
                "weight": -0.8538907328675189
            },
            "4": {
                "active": true,
                "nrn_to": 3,
                "nrn_from": 0,
                "weight": -0.9783923503490192
            },
            "69": {
                "active": true,
                "nrn_to": 23,
                "nrn_from": 2,
                "weight": 0.39013043157669247
            },
            "5": {
                "active": true,
                "nrn_to": 3,
                "nrn_from": 2,
                "weight": 0.25142899998605656
            },
            "6": {
                "active": false,
                "nrn_to": 3,
                "nrn_from": 1,
                "weight": 0.2741889388590227
            },
            "203": {
                "active": true,
                "nrn_to": 202,
                "nrn_from": 1,
                "weight": 1.974638314815907
            },
            "204": {
                "active": true,
                "nrn_to": 23,
                "nrn_from": 202,
                "weight": 0.9344333044449942
            },
            "214": {
                "active": true,
                "nrn_to": 202,
                "nrn_from": 0,
                "weight": 0.20333819744084328
            },
            "24": {
                "active": true,
                "nrn_to": 23,
                "nrn_from": 0,
                "weight": 1.1916873856999632
            },
            "25": {
                "active": true,
                "nrn_to": 3,
                "nrn_from": 23,
                "weight": -1.0351940864539944
            },
            "224": {
                "active": true,
                "nrn_to": 3,
                "nrn_from": 202,
                "weight": -0.5366269419262126
            }
        }
    }
}