{
    "Num species": 6,
    "Species 1 num animals": 3,
    "Species 1 top fitness": -3.866101805203252,
    "Species 1 mean fitness": -22.838844484442934,
    "Species 1 std fitness": 16.77344836718217,
    "Species 1 top animal N hidden neurons": 0,
    "Species 1 top animal N synapses": 21,
    "Species 1 top animal": {
        "neurons": {
            "0": {
                "type": "i",
                "bias": 0.43158685539721187
            },
            "1": {
                "type": "i",
                "bias": 0.07526936935481209
            },
            "2": {
                "type": "i",
                "bias": -2.0727743600749244
            },
            "3": {
                "type": "i",
                "bias": 2.939185074794434
            },
            "4": {
                "type": "i",
                "bias": 1.9795008975457717
            },
            "5": {
                "type": "i",
                "bias": 0.29139891730411244
            },
            "6": {
                "type": "i",
                "bias": -0.2524943214374837
            },
            "7": {
                "type": "i",
                "bias": 0.2003239951206922
            },
            "8": {
                "type": "o",
                "bias": -0.3073230078193637
            },
            "9": {
                "type": "o",
                "bias": -0.05375814123575842
            },
            "10": {
                "type": "o",
                "bias": 0.10535256266331636
            },
            "11": {
                "type": "o",
                "bias": 0.33865300253268416
            }
        },
        "synapses": {
            "12": {
                "nrn_to": 11,
                "nrn_from": 7,
                "weight": 0.0717747722465962,
                "active": true
            },
            "13": {
                "nrn_to": 11,
                "nrn_from": 0,
                "weight": -2.888233951670177,
                "active": false
            },
            "14": {
                "nrn_to": 9,
                "nrn_from": 1,
                "weight": -0.2643032347105735,
                "active": true
            },
            "15": {
                "nrn_to": 11,
                "nrn_from": 5,
                "weight": -0.09437383444602725,
                "active": false
            },
            "16": {
                "nrn_to": 8,
                "nrn_from": 1,
                "weight": -0.0007367519296852393,
                "active": false
            },
            "18": {
                "nrn_to": 8,
                "nrn_from": 2,
                "weight": 0.0036656543237188755,
                "active": true
            },
            "19": {
                "nrn_to": 8,
                "nrn_from": 3,
                "weight": 0.9399932443141712,
                "active": false
            },
            "21": {
                "nrn_to": 9,
                "nrn_from": 6,
                "weight": 0.16186093873140361,
                "active": true
            },
            "22": {
                "nrn_to": 9,
                "nrn_from": 0,
                "weight": 0.5484271050906586,
                "active": true
            },
            "23": {
                "nrn_to": 9,
                "nrn_from": 7,
                "weight": -0.22506545160550995,
                "active": true
            },
            "24": {
                "nrn_to": 9,
                "nrn_from": 4,
                "weight": -2.995018401410025,
                "active": true
            },
            "25": {
                "nrn_to": 10,
                "nrn_from": 5,
                "weight": -0.0329426861061215,
                "active": false
            },
            "26": {
                "nrn_to": 9,
                "nrn_from": 2,
                "weight": 0.3306322376576355,
                "active": true
            },
            "27": {
                "nrn_to": 9,
                "nrn_from": 3,
                "weight": 0.039820461593600066,
                "active": true
            },
            "28": {
                "nrn_to": 11,
                "nrn_from": 3,
                "weight": 0.3808245192197306,
                "active": true
            },
            "30": {
                "nrn_to": 9,
                "nrn_from": 5,
                "weight": -0.6278187156174897,
                "active": true
            },
            "35": {
                "nrn_to": 10,
                "nrn_from": 6,
                "weight": 0.07771153061470977,
                "active": false
            },
            "37": {
                "nrn_to": 10,
                "nrn_from": 3,
                "weight": -0.2456073687980889,
                "active": true
            },
            "42": {
                "nrn_to": 10,
                "nrn_from": 1,
                "weight": -0.278578446557781,
                "active": true
            },
            "49": {
                "nrn_to": 8,
                "nrn_from": 7,
                "weight": -0.002233560103364906,
                "active": false
            },
            "50": {
                "nrn_to": 11,
                "nrn_from": 2,
                "weight": 0.08900704897573067,
                "active": true
            }
        }
    },
    "Species 7 num animals": 10,
    "Species 7 top fitness": 132.58875390992026,
    "Species 7 mean fitness": 4.889777862124381,
    "Species 7 std fitness": 131.04145408991909,
    "Species 7 top animal N hidden neurons": 0,
    "Species 7 top animal N synapses": 24,
    "Species 7 top animal": {
        "neurons": {
            "0": {
                "type": "i",
                "bias": -0.7239866003298515
            },
            "1": {
                "type": "i",
                "bias": -0.18043535520562753
            },
            "2": {
                "type": "i",
                "bias": -0.16746307656945086
            },
            "3": {
                "type": "i",
                "bias": 0.2309107409357029
            },
            "4": {
                "type": "i",
                "bias": 0.9014034181038405
            },
            "5": {
                "type": "i",
                "bias": 1.5480487098040832
            },
            "6": {
                "type": "i",
                "bias": 0.031015310084973775
            },
            "7": {
                "type": "i",
                "bias": 0.3641742338332937
            },
            "8": {
                "type": "o",
                "bias": -0.003363629211192781
            },
            "9": {
                "type": "o",
                "bias": 0.601436778466075
            },
            "10": {
                "type": "o",
                "bias": 0.250753306153152
            },
            "11": {
                "type": "o",
                "bias": 0.9692250518196559
            }
        },
        "synapses": {
            "65": {
                "nrn_to": 8,
                "nrn_from": 4,
                "weight": -1.6355104833062584,
                "active": true
            },
            "12": {
                "nrn_to": 11,
                "nrn_from": 7,
                "weight": 0.1540786542037305,
                "active": false
            },
            "13": {
                "nrn_to": 11,
                "nrn_from": 0,
                "weight": 0.3260128662172354,
                "active": false
            },
            "15": {
                "nrn_to": 11,
                "nrn_from": 5,
                "weight": 0.7921528561378955,
                "active": true
            },
            "16": {
                "nrn_to": 8,
                "nrn_from": 1,
                "weight": 0.4161094152728413,
                "active": false
            },
            "17": {
                "nrn_to": 11,
                "nrn_from": 1,
                "weight": -0.02743673255392137,
                "active": true
            },
            "19": {
                "nrn_to": 8,
                "nrn_from": 3,
                "weight": 0.16420453050798858,
                "active": true
            },
            "20": {
                "nrn_to": 8,
                "nrn_from": 6,
                "weight": -0.7581580504828219,
                "active": true
            },
            "22": {
                "nrn_to": 9,
                "nrn_from": 0,
                "weight": 0.6352386195960451,
                "active": true
            },
            "23": {
                "nrn_to": 9,
                "nrn_from": 7,
                "weight": -0.7339593708541248,
                "active": true
            },
            "24": {
                "nrn_to": 9,
                "nrn_from": 4,
                "weight": -1.851571855115625,
                "active": true
            },
            "26": {
                "nrn_to": 9,
                "nrn_from": 2,
                "weight": 0.07356039305957263,
                "active": false
            },
            "28": {
                "nrn_to": 11,
                "nrn_from": 3,
                "weight": 0.9059810212334305,
                "active": true
            },
            "29": {
                "nrn_to": 11,
                "nrn_from": 6,
                "weight": -0.04553607313488701,
                "active": true
            },
            "31": {
                "nrn_to": 10,
                "nrn_from": 2,
                "weight": -0.35358688383752657,
                "active": true
            },
            "32": {
                "nrn_to": 10,
                "nrn_from": 0,
                "weight": 0.22155029801052284,
                "active": true
            },
            "33": {
                "nrn_to": 8,
                "nrn_from": 0,
                "weight": -0.3509092031601977,
                "active": true
            },
            "34": {
                "nrn_to": 10,
                "nrn_from": 7,
                "weight": -0.31997532834519854,
                "active": true
            },
            "35": {
                "nrn_to": 10,
                "nrn_from": 6,
                "weight": 0.6687908543028236,
                "active": true
            },
            "36": {
                "nrn_to": 11,
                "nrn_from": 4,
                "weight": -0.3570549803477633,
                "active": true
            },
            "37": {
                "nrn_to": 10,
                "nrn_from": 3,
                "weight": -1.7083373682070486,
                "active": true
            },
            "42": {
                "nrn_to": 10,
                "nrn_from": 1,
                "weight": -0.5931441787776042,
                "active": false
            },
            "49": {
                "nrn_to": 8,
                "nrn_from": 7,
                "weight": -0.0009214006475072381,
                "active": false
            },
            "58": {
                "nrn_to": 10,
                "nrn_from": 4,
                "weight": -0.06562468616389378,
                "active": false
            }
        }
    },
    "Species 3 num animals": 10,
    "Species 3 top fitness": 208.86493038526018,
    "Species 3 mean fitness": 111.62858978619565,
    "Species 3 std fitness": 94.14415798562553,
    "Species 3 top animal N hidden neurons": 1,
    "Species 3 top animal N synapses": 25,
    "Species 3 top animal": {
        "neurons": {
            "0": {
                "type": "i",
                "bias": -0.6023132263897967
            },
            "1": {
                "type": "i",
                "bias": -0.2522810006790828
            },
            "2": {
                "type": "i",
                "bias": 0.04454097614765215
            },
            "3": {
                "type": "i",
                "bias": 1.9566114099694007
            },
            "4": {
                "type": "i",
                "bias": 0.27992204355700023
            },
            "5": {
                "type": "i",
                "bias": 0.11919761373594308
            },
            "6": {
                "type": "i",
                "bias": -0.09083219705612564
            },
            "7": {
                "type": "i",
                "bias": -0.5774988952761687
            },
            "8": {
                "type": "o",
                "bias": -0.3278116097681326
            },
            "9": {
                "type": "o",
                "bias": 0.14549679577227229
            },
            "10": {
                "type": "o",
                "bias": -0.02130290167594546
            },
            "11": {
                "type": "o",
                "bias": 0.2668316427690415
            },
            "249": {
                "type": "h",
                "bias": -0.050294007097668215
            }
        },
        "synapses": {
            "65": {
                "nrn_to": 8,
                "nrn_from": 4,
                "weight": -1.5638267057757884,
                "active": true
            },
            "267": {
                "nrn_to": 249,
                "nrn_from": 0,
                "weight": 0.23985511673504764,
                "active": true
            },
            "12": {
                "nrn_to": 11,
                "nrn_from": 7,
                "weight": -0.23189125334694513,
                "active": false
            },
            "13": {
                "nrn_to": 11,
                "nrn_from": 0,
                "weight": 0.7045943771275557,
                "active": false
            },
            "271": {
                "nrn_to": 249,
                "nrn_from": 2,
                "weight": 0.2626835804020587,
                "active": true
            },
            "16": {
                "nrn_to": 8,
                "nrn_from": 1,
                "weight": 0.14082548118093993,
                "active": false
            },
            "15": {
                "nrn_to": 11,
                "nrn_from": 5,
                "weight": 0.21503517930953697,
                "active": true
            },
            "20": {
                "nrn_to": 8,
                "nrn_from": 6,
                "weight": -2.714939024438058,
                "active": true
            },
            "22": {
                "nrn_to": 9,
                "nrn_from": 0,
                "weight": 0.6115142807446683,
                "active": true
            },
            "23": {
                "nrn_to": 9,
                "nrn_from": 7,
                "weight": -0.15958006241758396,
                "active": true
            },
            "24": {
                "nrn_to": 9,
                "nrn_from": 4,
                "weight": -1.1170413469902603,
                "active": true
            },
            "278": {
                "nrn_to": 249,
                "nrn_from": 1,
                "weight": 0.9163103363768881,
                "active": true
            },
            "282": {
                "nrn_to": 249,
                "nrn_from": 5,
                "weight": 0.1617291057551597,
                "active": false
            },
            "26": {
                "nrn_to": 9,
                "nrn_from": 2,
                "weight": 0.41388099865647776,
                "active": true
            },
            "283": {
                "nrn_to": 249,
                "nrn_from": 4,
                "weight": -0.17906876517656406,
                "active": true
            },
            "28": {
                "nrn_to": 11,
                "nrn_from": 3,
                "weight": 0.34511642637542495,
                "active": false
            },
            "29": {
                "nrn_to": 11,
                "nrn_from": 6,
                "weight": 0.3022417758123057,
                "active": true
            },
            "287": {
                "nrn_to": 8,
                "nrn_from": 249,
                "weight": -0.30108268860662735,
                "active": true
            },
            "34": {
                "nrn_to": 10,
                "nrn_from": 7,
                "weight": -0.03476193184909669,
                "active": false
            },
            "35": {
                "nrn_to": 10,
                "nrn_from": 6,
                "weight": 0.34971238976291236,
                "active": true
            },
            "37": {
                "nrn_to": 10,
                "nrn_from": 3,
                "weight": -1.5123661551101666,
                "active": true
            },
            "42": {
                "nrn_to": 10,
                "nrn_from": 1,
                "weight": -0.2875709287009393,
                "active": true
            },
            "49": {
                "nrn_to": 8,
                "nrn_from": 7,
                "weight": -0.4067710486261209,
                "active": true
            },
            "250": {
                "active": false,
                "nrn_to": 249,
                "nrn_from": 7,
                "weight": 0.4381237886173111
            },
            "251": {
                "active": true,
                "nrn_to": 10,
                "nrn_from": 249,
                "weight": -0.15910810662788008
            }
        }
    },
    "Species 9 num animals": 16,
    "Species 9 top fitness": 174.8847130836685,
    "Species 9 mean fitness": 66.54425608964625,
    "Species 9 std fitness": 175.87949589445705,
    "Species 9 top animal N hidden neurons": 1,
    "Species 9 top animal N synapses": 28,
    "Species 9 top animal": {
        "neurons": {
            "0": {
                "type": "i",
                "bias": -0.10690704451701262
            },
            "1": {
                "type": "i",
                "bias": -1.2637109201305579
            },
            "2": {
                "type": "i",
                "bias": 0.051199212323767306
            },
            "3": {
                "type": "i",
                "bias": 2.824042464556539
            },
            "4": {
                "type": "i",
                "bias": 0.12864006568244898
            },
            "5": {
                "type": "i",
                "bias": -0.10579643943082163
            },
            "6": {
                "type": "i",
                "bias": -0.1995518883766304
            },
            "7": {
                "type": "i",
                "bias": -0.6846574352577249
            },
            "8": {
                "type": "o",
                "bias": -0.4511350472390348
            },
            "9": {
                "type": "o",
                "bias": 0.1481419353364642
            },
            "10": {
                "type": "o",
                "bias": -0.0184284965101268
            },
            "11": {
                "type": "o",
                "bias": 0.20653989330418895
            },
            "249": {
                "type": "h",
                "bias": -0.03126443188670612
            }
        },
        "synapses": {
            "65": {
                "nrn_to": 8,
                "nrn_from": 4,
                "weight": -1.396744115002697,
                "active": true
            },
            "267": {
                "nrn_to": 249,
                "nrn_from": 0,
                "weight": -0.008111329571864695,
                "active": true
            },
            "12": {
                "nrn_to": 11,
                "nrn_from": 7,
                "weight": -0.030394625613829555,
                "active": false
            },
            "13": {
                "nrn_to": 11,
                "nrn_from": 0,
                "weight": 0.35946856872977906,
                "active": false
            },
            "15": {
                "nrn_to": 11,
                "nrn_from": 5,
                "weight": 0.62585567201926,
                "active": true
            },
            "16": {
                "nrn_to": 8,
                "nrn_from": 1,
                "weight": 0.37367097159355983,
                "active": false
            },
            "271": {
                "nrn_to": 249,
                "nrn_from": 2,
                "weight": 0.1211194899248258,
                "active": true
            },
            "18": {
                "nrn_to": 8,
                "nrn_from": 2,
                "weight": 0.0997052087298681,
                "active": true
            },
            "19": {
                "nrn_to": 8,
                "nrn_from": 3,
                "weight": 0.3367105499656531,
                "active": false
            },
            "20": {
                "nrn_to": 8,
                "nrn_from": 6,
                "weight": -0.688559074183776,
                "active": true
            },
            "21": {
                "nrn_to": 9,
                "nrn_from": 6,
                "weight": 0.3401322221994251,
                "active": true
            },
            "22": {
                "nrn_to": 9,
                "nrn_from": 0,
                "weight": 0.36480577965004646,
                "active": true
            },
            "23": {
                "nrn_to": 9,
                "nrn_from": 7,
                "weight": 0.11102573337713312,
                "active": false
            },
            "24": {
                "nrn_to": 9,
                "nrn_from": 4,
                "weight": -1.026324607540807,
                "active": true
            },
            "278": {
                "nrn_to": 249,
                "nrn_from": 1,
                "weight": 1.5055473060766587,
                "active": true
            },
            "282": {
                "nrn_to": 249,
                "nrn_from": 5,
                "weight": 0.07631363441098071,
                "active": false
            },
            "26": {
                "nrn_to": 9,
                "nrn_from": 2,
                "weight": 0.479759174431152,
                "active": true
            },
            "283": {
                "nrn_to": 249,
                "nrn_from": 4,
                "weight": 0.31819810631418277,
                "active": true
            },
            "28": {
                "nrn_to": 11,
                "nrn_from": 3,
                "weight": 0.030178105722315555,
                "active": true
            },
            "29": {
                "nrn_to": 11,
                "nrn_from": 6,
                "weight": 0.7351824832104038,
                "active": true
            },
            "34": {
                "nrn_to": 10,
                "nrn_from": 7,
                "weight": -0.29056660887978153,
                "active": false
            },
            "35": {
                "nrn_to": 10,
                "nrn_from": 6,
                "weight": 0.07615840138427434,
                "active": true
            },
            "37": {
                "nrn_to": 10,
                "nrn_from": 3,
                "weight": -1.7336758680744422,
                "active": true
            },
            "41": {
                "nrn_to": 8,
                "nrn_from": 5,
                "weight": -0.5008896018671399,
                "active": true
            },
            "42": {
                "nrn_to": 10,
                "nrn_from": 1,
                "weight": 0.05022960284054813,
                "active": true
            },
            "250": {
                "active": true,
                "nrn_to": 249,
                "nrn_from": 7,
                "weight": 0.8102275373108114
            },
            "58": {
                "nrn_to": 10,
                "nrn_from": 4,
                "weight": 0.3226909169067365,
                "active": true
            },
            "251": {
                "active": true,
                "nrn_to": 10,
                "nrn_from": 249,
                "weight": -0.28073924538921463
            }
        }
    },
    "Species 2 num animals": 7,
    "Species 2 top fitness": -25.158639731151837,
    "Species 2 mean fitness": -77.20588927066454,
    "Species 2 std fitness": 68.28939648368208,
    "Species 2 top animal N hidden neurons": 2,
    "Species 2 top animal N synapses": 26,
    "Species 2 top animal": {
        "neurons": {
            "0": {
                "type": "i",
                "bias": 0.4305903828698491
            },
            "1": {
                "type": "i",
                "bias": 0.21691324402137188
            },
            "2": {
                "type": "i",
                "bias": -0.817687228884295
            },
            "3": {
                "type": "i",
                "bias": 0.4247641423282619
            },
            "4": {
                "type": "i",
                "bias": 0.08884002995456754
            },
            "5": {
                "type": "i",
                "bias": 0.08067949959879953
            },
            "6": {
                "type": "i",
                "bias": -0.7791248569123849
            },
            "7": {
                "type": "i",
                "bias": 0.06550181797145051
            },
            "8": {
                "type": "o",
                "bias": 0.0921700904421872
            },
            "9": {
                "type": "o",
                "bias": -0.029231866782671742
            },
            "10": {
                "type": "o",
                "bias": 0.14748664281073504
            },
            "11": {
                "type": "o",
                "bias": -0.03895938556239069
            },
            "332": {
                "type": "h",
                "bias": 0.10165720325761196
            },
            "147": {
                "type": "h",
                "bias": 0.15016285654192696
            }
        },
        "synapses": {
            "65": {
                "nrn_to": 8,
                "nrn_from": 4,
                "weight": 0.09242556936672038,
                "active": true
            },
            "13": {
                "nrn_to": 11,
                "nrn_from": 0,
                "weight": 0.10304846053155367,
                "active": false
            },
            "333": {
                "active": true,
                "nrn_to": 332,
                "nrn_from": 5,
                "weight": 0.25706980477931407
            },
            "15": {
                "nrn_to": 11,
                "nrn_from": 5,
                "weight": 0.6905210526705875,
                "active": true
            },
            "16": {
                "nrn_to": 8,
                "nrn_from": 1,
                "weight": -0.13214655718417798,
                "active": false
            },
            "17": {
                "nrn_to": 11,
                "nrn_from": 1,
                "weight": 0.47727188021337574,
                "active": true
            },
            "334": {
                "active": true,
                "nrn_to": 147,
                "nrn_from": 332,
                "weight": 2.219949894646921
            },
            "148": {
                "active": true,
                "nrn_to": 147,
                "nrn_from": 5,
                "weight": 0.5991397645047781
            },
            "149": {
                "active": false,
                "nrn_to": 8,
                "nrn_from": 147,
                "weight": -2.940327199882096
            },
            "20": {
                "nrn_to": 8,
                "nrn_from": 6,
                "weight": 0.3283742245555494,
                "active": false
            },
            "23": {
                "nrn_to": 9,
                "nrn_from": 7,
                "weight": 2.2731397837690586,
                "active": false
            },
            "24": {
                "nrn_to": 9,
                "nrn_from": 4,
                "weight": -2.839615039058439,
                "active": true
            },
            "25": {
                "nrn_to": 10,
                "nrn_from": 5,
                "weight": 0.6754862735594798,
                "active": true
            },
            "26": {
                "nrn_to": 9,
                "nrn_from": 2,
                "weight": -0.20221321387840163,
                "active": false
            },
            "343": {
                "nrn_to": 9,
                "nrn_from": 332,
                "weight": -0.18523225515263095,
                "active": true
            },
            "32": {
                "nrn_to": 10,
                "nrn_from": 0,
                "weight": -0.04096185819447405,
                "active": false
            },
            "161": {
                "nrn_to": 10,
                "nrn_from": 147,
                "weight": 0.03938300681495877,
                "active": false
            },
            "34": {
                "nrn_to": 10,
                "nrn_from": 7,
                "weight": -0.279372309916042,
                "active": false
            },
            "35": {
                "nrn_to": 10,
                "nrn_from": 6,
                "weight": -0.5486315395923355,
                "active": true
            },
            "36": {
                "nrn_to": 11,
                "nrn_from": 4,
                "weight": 2.983324249742688,
                "active": true
            },
            "163": {
                "nrn_to": 147,
                "nrn_from": 4,
                "weight": 0.4073336033901731,
                "active": false
            },
            "162": {
                "nrn_to": 147,
                "nrn_from": 7,
                "weight": 0.31536467379335353,
                "active": false
            },
            "227": {
                "nrn_to": 11,
                "nrn_from": 147,
                "weight": 0.16952680644968393,
                "active": false
            },
            "41": {
                "nrn_to": 8,
                "nrn_from": 5,
                "weight": 0.0782943380448706,
                "active": false
            },
            "170": {
                "nrn_to": 147,
                "nrn_from": 0,
                "weight": -0.03759992862641272,
                "active": false
            },
            "370": {
                "nrn_to": 332,
                "nrn_from": 3,
                "weight": -0.03196012689823853,
                "active": true
            }
        }
    },
    "Species 6 num animals": 14,
    "Species 6 top fitness": 190.46732172969385,
    "Species 6 mean fitness": 108.63591121361377,
    "Species 6 std fitness": 51.32348237929454,
    "Species 6 top animal N hidden neurons": 0,
    "Species 6 top animal N synapses": 22,
    "Species 6 top animal": {
        "neurons": {
            "0": {
                "type": "i",
                "bias": -0.23515936955022462
            },
            "1": {
                "type": "i",
                "bias": -0.007240121728469856
            },
            "2": {
                "type": "i",
                "bias": 0.12374032413822401
            },
            "3": {
                "type": "i",
                "bias": 3.0
            },
            "4": {
                "type": "i",
                "bias": -0.021403905869081145
            },
            "5": {
                "type": "i",
                "bias": 0.4507783552328918
            },
            "6": {
                "type": "i",
                "bias": -0.06989879594040416
            },
            "7": {
                "type": "i",
                "bias": 0.022777393310645114
            },
            "8": {
                "type": "o",
                "bias": -0.4842908216959983
            },
            "9": {
                "type": "o",
                "bias": 0.2013137962963586
            },
            "10": {
                "type": "o",
                "bias": 0.12107364420441816
            },
            "11": {
                "type": "o",
                "bias": 0.3316933274565244
            }
        },
        "synapses": {
            "65": {
                "nrn_to": 8,
                "nrn_from": 4,
                "weight": -0.44829671997634624,
                "active": false
            },
            "12": {
                "nrn_to": 11,
                "nrn_from": 7,
                "weight": 0.1375942758097393,
                "active": false
            },
            "13": {
                "nrn_to": 11,
                "nrn_from": 0,
                "weight": 0.09708195722140746,
                "active": false
            },
            "15": {
                "nrn_to": 11,
                "nrn_from": 5,
                "weight": 0.4504564882030614,
                "active": true
            },
            "16": {
                "nrn_to": 8,
                "nrn_from": 1,
                "weight": 0.4784047580230639,
                "active": false
            },
            "20": {
                "nrn_to": 8,
                "nrn_from": 6,
                "weight": -1.4888607295705396,
                "active": true
            },
            "22": {
                "nrn_to": 9,
                "nrn_from": 0,
                "weight": 0.4322077969260113,
                "active": true
            },
            "23": {
                "nrn_to": 9,
                "nrn_from": 7,
                "weight": -0.3290471545680321,
                "active": true
            },
            "24": {
                "nrn_to": 9,
                "nrn_from": 4,
                "weight": -1.2474110676476835,
                "active": true
            },
            "25": {
                "nrn_to": 10,
                "nrn_from": 5,
                "weight": -0.21847340061977674,
                "active": true
            },
            "26": {
                "nrn_to": 9,
                "nrn_from": 2,
                "weight": 0.31205988236236076,
                "active": true
            },
            "27": {
                "nrn_to": 9,
                "nrn_from": 3,
                "weight": -0.2182651677243015,
                "active": false
            },
            "28": {
                "nrn_to": 11,
                "nrn_from": 3,
                "weight": 0.5197150068176254,
                "active": true
            },
            "32": {
                "nrn_to": 10,
                "nrn_from": 0,
                "weight": -2.8371868852919424e-05,
                "active": false
            },
            "33": {
                "nrn_to": 8,
                "nrn_from": 0,
                "weight": -0.2570708384818431,
                "active": true
            },
            "34": {
                "nrn_to": 10,
                "nrn_from": 7,
                "weight": -0.9934702783064288,
                "active": true
            },
            "35": {
                "nrn_to": 10,
                "nrn_from": 6,
                "weight": 1.0825541549037414,
                "active": true
            },
            "36": {
                "nrn_to": 11,
                "nrn_from": 4,
                "weight": -0.2626391079633396,
                "active": false
            },
            "37": {
                "nrn_to": 10,
                "nrn_from": 3,
                "weight": -0.5681210405952651,
                "active": true
            },
            "42": {
                "nrn_to": 10,
                "nrn_from": 1,
                "weight": 0.027604425236266557,
                "active": false
            },
            "49": {
                "nrn_to": 8,
                "nrn_from": 7,
                "weight": 0.32572538122545897,
                "active": true
            },
            "50": {
                "nrn_to": 11,
                "nrn_from": 2,
                "weight": -0.6849733883665505,
                "active": true
            }
        }
    }
}